odoo/addons/shopinvader_search_engine_update_product_brand/README.rst
odoo/addons/shopinvader_search_engine_update_product_brand/__init__.py
odoo/addons/shopinvader_search_engine_update_product_brand/__manifest__.py
odoo/addons/shopinvader_search_engine_update_product_brand/i18n/shopinvader_search_engine_update_product_brand.pot
odoo/addons/shopinvader_search_engine_update_product_brand/models/__init__.py
odoo/addons/shopinvader_search_engine_update_product_brand/models/product_brand.py
odoo/addons/shopinvader_search_engine_update_product_brand/readme/CONTEXT.md
odoo/addons/shopinvader_search_engine_update_product_brand/readme/CONTRIBUTORS.md
odoo/addons/shopinvader_search_engine_update_product_brand/readme/DESCRIPTION.md
odoo/addons/shopinvader_search_engine_update_product_brand/static/description/icon.png
odoo/addons/shopinvader_search_engine_update_product_brand/static/description/index.html
odoo/addons/shopinvader_search_engine_update_product_brand/tests/__init__.py
odoo/addons/shopinvader_search_engine_update_product_brand/tests/common.py
odoo/addons/shopinvader_search_engine_update_product_brand/tests/test_update.py
odoo_addon_shopinvader_search_engine_update_product_brand-16.0.1.0.0.2.dist-info/METADATA
odoo_addon_shopinvader_search_engine_update_product_brand-16.0.1.0.0.2.dist-info/WHEEL
odoo_addon_shopinvader_search_engine_update_product_brand-16.0.1.0.0.2.dist-info/top_level.txt
odoo_addon_shopinvader_search_engine_update_product_brand-16.0.1.0.0.2.dist-info/RECORD
